ingest_data.py
score.py
train.py
housing_library_5520-0.1.dist-info/METADATA
housing_library_5520-0.1.dist-info/WHEEL
housing_library_5520-0.1.dist-info/entry_points.txt
housing_library_5520-0.1.dist-info/top_level.txt
housing_library_5520-0.1.dist-info/RECORD
